MCP-Neuron_v0/Verilog/neuronode.sv
// 2 Input MCP Neuron
module neuronode (
  input logic x,
  input logic y,
  input logic [1:0] Threshold,
  output logic fire
  );

  logic [1:0] sum;
  assign sum = x + y;

  always_comb begin
    if ( sum >= Threshold ) begin
        fire = 1'b1;
    end else begin
        fire = 1'b0;
    end
  end       
endmodule

MCP-Neuron_v0/Verilog/neuronode_tb.sv
`include "neuronode.sv"

module neuronode_tb;
    logic x_in;
    logic y_in;
    logic [1:0] thresh_in;
    logic fire_out;

    neuronode dut (
        .x(x_in),
        .y(y_in),
        .Threshold(thresh_in),
        .fire(fire_out)
    );

    initial begin
        $dumpfile("neuronode.vcd");
        $dumpvars(0, neuronode_tb);
        $monitor("t = %0t | x_in = %b | y_in = %b | fire_out = %b", $time, x_in, y_in, fire_out);
        
        $display("Testing Threshold = 2 (AND Logic)");
        thresh_in = 2; 
        
        x_in = 0; y_in = 0; #10;
        x_in = 0; y_in = 1; #10;
        x_in = 1; y_in = 0; #10;
        x_in = 1; y_in = 1; #10; 

        $display("Testing Threshold = 1 (OR Logic)");
        thresh_in = 1;

        x_in = 0; y_in = 0; #10;
        x_in = 0; y_in = 1; #10;
        x_in = 1; y_in = 0; #10;
        x_in = 1; y_in = 1; #10;

        $finish;
    end

endmodule

MCP-Neuron_v0/neuronode.vcd
$date
	Sun Jan 11 17:39:24 2026
$end
$version
	Icarus Verilog
$end
$timescale
	1s
$end
$scope module neuronode_tb $end
$var wire 1 ! fire_out $end
$var reg 2 " thresh_in [1:0] $end
$var reg 1 # x_in $end
$var reg 1 $ y_in $end
$scope module dut $end
$var wire 2 % Threshold [1:0] $end
$var wire 1 # x $end
$var wire 1 $ y $end
$var wire 2 & sum [1:0] $end
$var reg 1 ! fire $end
$upscope $end
$upscope $end
$enddefinitions $end
$comment Show the parameter values. $end
$dumpall
$end
#0
$dumpvars
b0 &
b10 %
0$
0#
b10 "
0!
$end
#10
b1 &
1$
#20
0$
b1 &
1#
#30
1!
b10 &
1$
#40
0!
0$
b0 &
0#
b1 "
b1 %
#50
1!
b1 &
1$
#60
0$
b1 &
1#
#70
b10 &
1$
