MCP-Neuron_v0/neuronode.vhd
library ieee;
use ieee.std_logic_1164.all;
use ieee.numeric_std.all;

entity neuronode is
    port (
        x      : in  std_logic;  -- input 1 (0 or 1)
        y      : in  std_logic;  -- input 2 (0 or 1)
        thresh : in  integer;    -- threshold
        fire   : out std_logic   -- neuron output
    );
end neuronode;

architecture rtl of neuronode is
begin
    process(x, y, thresh)
        variable sum : integer;
    begin
        sum := 0;

        if x = '1' then
            sum := sum + 1;
        end if;

        if y = '1' then
            sum := sum + 1;
        end if;

        if sum >= thresh then
            fire <= '1';
        else
            fire <= '0';
        end if;
    end process;
end rtl;

MCP-Neuron_v0/VHDL/tb_neuronode.vhdl
-- Testbench for neuronode (VHDL)
-- Verifies neuron firing behavior across two threshold settings
library ieee;
use ieee.std_logic_1164.all;

entity tb_neuronode is
end tb_neuronode;

architecture sim of tb_neuronode is

    -- Signals driven by testbench
    signal x, y   : std_logic := '0';
    signal thresh : integer := 1;

    -- Output observed from the neuron
    signal fire   : std_logic;

begin

    -- Instantiate the neuron under test
    uut: entity work.neuronode
        port map (
            x      => x,
            y      => y,
            thresh => thresh,
            fire   => fire
        );

    process
    begin
        -- Test 1: Threshold = 1 (OR Logic, either input triggers fire)
        thresh <= 1;
        x <= '0'; y <= '0'; wait for 10 ns; -- sum = 0, no fire
        x <= '0'; y <= '1'; wait for 10 ns; -- sum = 1, fires
        x <= '1'; y <= '0'; wait for 10 ns; -- sum = 1, fires
        x <= '1'; y <= '1'; wait for 10 ns; -- sum = 2, fires

        -- Test 2: Threshold = 2 (AND Logic, both inputs must be 1)
        thresh <= 2;
        x <= '0'; y <= '0'; wait for 10 ns; -- sum = 0, no fire
        x <= '0'; y <= '1'; wait for 10 ns; -- sum = 1, no fire
        x <= '1'; y <= '0'; wait for 10 ns; -- sum = 1, no fire
        x <= '1'; y <= '1'; wait for 10 ns; -- sum = 2, fires

        wait; -- End simulation
    end process;

end sim;

MCP-Neuron_v0/vhdlsim.vcd
$date
  Tue Jan 20 21:11:19 2026
$end
$version
  GHDL v0
$end
$timescale
  1 fs
$end
$scope module standard $end
$upscope $end
$scope module std_logic_1164 $end
$upscope $end
$scope module numeric_std $end
$upscope $end
$scope module tb_neuronode $end
$var reg 1 ! x $end
$var reg 1 " y $end
$var integer 32 # thresh $end
$var reg 1 $ fire $end
$scope module uut $end
$var reg 1 % x $end
$var reg 1 & y $end
$var integer 32 ' thresh $end
$var reg 1 ( fire $end
$upscope $end
$upscope $end
$enddefinitions $end
#0
0!
0"
b1 #
0$
0%
0&
b1 '
0(
#10000000
1"
1$
1&
1(
#20000000
1!
0"
1%
0&
#30000000
1"
1&
#40000000
0!
0"
b10 #
0$
0%
0&
b10 '
0(
#50000000
1"
1&
#60000000
1!
0"
1%
0&
#70000000
1"
1$
1&
1(
